foliant/preprocessors/flatten.py
foliantcontrib.flatten-1.0.7.dist-info/LICENSE
foliantcontrib.flatten-1.0.7.dist-info/METADATA
foliantcontrib.flatten-1.0.7.dist-info/WHEEL
foliantcontrib.flatten-1.0.7.dist-info/top_level.txt
foliantcontrib.flatten-1.0.7.dist-info/RECORD
