Metadata-Version: 2.1
Name: foliantcontrib.flatten
Version: 1.0.7
Summary: Preprocessor for Foliant doc maker that flattens a nested source tree into a single file. Required for Pandoc backend.
Home-page: https://github.com/foliant-docs/foliantcontrib.flatten
Author: Konstantin Molchanov
Author-email: moigagoo@live.com
License: MIT
Platform: any
Classifier: Development Status :: 5 - Production/Stable
Classifier: Environment :: Console
Classifier: Intended Audience :: Developers
Classifier: License :: OSI Approved :: MIT License
Classifier: Operating System :: OS Independent
Classifier: Programming Language :: Python
Classifier: Topic :: Documentation
Classifier: Topic :: Utilities
Requires-Dist: foliant (>=1.0.5)
Requires-Dist: foliantcontrib.includes (>=1.0.7)
